seffybacktest/.DS_Store
seffybacktest/__init__.py
seffybacktest/adjusted_sharpe.py
seffybacktest/annual_return.py
seffybacktest/average_returns.py
seffybacktest/benchmarking.py
seffybacktest/calmar_ratio.py
seffybacktest/capm_calculation.py
seffybacktest/correlation.py
seffybacktest/cvar_calculator.py
seffybacktest/double_sharpe.py
seffybacktest/famafrench.py
seffybacktest/get_portfolio_returns.py
seffybacktest/intraweek_variances.py
seffybacktest/market_alpha.py
seffybacktest/market_beta.py
seffybacktest/modified_sharpe.py
seffybacktest/momentum.py
seffybacktest/rsi.py
seffybacktest/seffybacktest.py
seffybacktest/sharpe_ratio.py
seffybacktest/sortino_ratio.py
seffybacktest/treynor_ratio.py
seffybacktest/var_calculator.py
seffybacktest/volatility.py
seffybacktest-1.3.0.dist-info/LICENSE.txt
seffybacktest-1.3.0.dist-info/METADATA
seffybacktest-1.3.0.dist-info/WHEEL
seffybacktest-1.3.0.dist-info/RECORD
