Metadata-Version: 2.1
Name: seffybacktest
Version: 1.3.0
Summary: This is a statisical portfolio analysis tool built to facilitate quantitative systems at The Equate Fund - UofT
License: MIT
Author: Youssef Hany Saad
Requires-Python: >=3.10,<4.0
Classifier: License :: OSI Approved :: MIT License
Classifier: Programming Language :: Python :: 3
Classifier: Programming Language :: Python :: 3.10
Classifier: Programming Language :: Python :: 3.11
Classifier: Programming Language :: Python :: 3.12
Requires-Dist: DateTime (>=5.5,<6.0)
Requires-Dist: matplotlib (>=3.9.1,<4.0.0)
Requires-Dist: numpy (>=2.0.0,<3.0.0)
Requires-Dist: pandas (>=2.2.2,<3.0.0)
Requires-Dist: scikit-learn (>=1.5,<2.0)
Requires-Dist: scipy (>=1.14.0,<2.0.0)
Requires-Dist: yfinance (>=0.2.40,<0.3.0)
